test_generator/__init__.py
test_generator/__version__.py
test_generator/chatgpt_handler.py
test_generator/generate_scenarios.py
test_generator/py.typed
test_generator/api_handlers/__init__.py
test_generator/api_handlers/api_file_updater.py
test_generator/api_handlers/api_generator.py
test_generator/api_handlers/templates/api_template.jinja
test_generator/helpers/__init__.py
test_generator/helpers/path.py
test_generator/library/__init__.py
test_generator/library/colors.py
test_generator/library/errors.py
test_generator/library/gena_data.py
test_generator/library/generate_component.py
test_generator/library/scenario.py
test_generator/library/suite.py
test_generator/md_handlers/__init__.py
test_generator/md_handlers/const.py
test_generator/md_handlers/md_handler.py
test_generator/md_handlers/md_list_handler.py
test_generator/md_handlers/md_table_handler.py
test_generator/md_handlers/templates/md_list_format.jinja
test_generator/md_handlers/templates/md_table_format.jinja
test_generator/schema_handlers/__init__.py
test_generator/schema_handlers/schema_file_creator.py
test_generator/schema_handlers/schema_generator.py
test_generator/test_readers/__init__.py
test_generator/test_readers/base_reader.py
test_generator/test_readers/vedro_reader.py
test_generator/test_writers/__init__.py
test_generator/test_writers/base_writer.py
test_generator/test_writers/separate_file_writer.py
gena_test_generator-0.0.4.dist-info/LICENSE
gena_test_generator-0.0.4.dist-info/METADATA
gena_test_generator-0.0.4.dist-info/WHEEL
gena_test_generator-0.0.4.dist-info/entry_points.txt
gena_test_generator-0.0.4.dist-info/top_level.txt
gena_test_generator-0.0.4.dist-info/RECORD
