Metadata-Version: 2.1
Name: gena-test-generator
Version: 0.0.4
Summary: Script for generating tests from Markdown files
Home-page: https://github.com/miner34006/gena-test-generator
License: Apache-2.0
Classifier: License :: OSI Approved :: Apache Software License
Classifier: Programming Language :: Python :: 3.7
Classifier: Programming Language :: Python :: 3.8
Classifier: Programming Language :: Python :: 3.9
Classifier: Programming Language :: Python :: 3.10
Requires-Python: >=3.7
License-File: LICENSE
Requires-Dist: openai==1.40.8
Requires-Dist: tabulate==0.9.0
Requires-Dist: types-tabulate==0.9.0.20240106
Requires-Dist: schemax==0.3.0
Requires-Dist: schemax-openapi==0.0.4
Requires-Dist: PyYAML==6.0.2
Requires-Dist: types-PyYAML==6.0.12.20240808
Requires-Dist: bump==1.3.2
Requires-Dist: Jinja2==3.1.4
